spriteutil_final/__init__.py
spriteutil_final/spriteutil.py
spriteutil_longlamduc-1.0.0.dist-info/LICENSE
spriteutil_longlamduc-1.0.0.dist-info/METADATA
spriteutil_longlamduc-1.0.0.dist-info/WHEEL
spriteutil_longlamduc-1.0.0.dist-info/top_level.txt
spriteutil_longlamduc-1.0.0.dist-info/RECORD
