Metadata-Version: 2.1
Name: spriteutil-longlamduc
Version: 1.0.0
Summary: A sprite detection package
Home-page: https://github.com/intek-training-jsc/sprite-detection-longlamduc.git
Author: Long Lam Duc
Author-email: long.lam@f4.intek.edu.vn
License: UNKNOWN
Platform: UNKNOWN
Classifier: Programming Language :: Python :: 3
Classifier: License :: OSI Approved :: MIT License
Classifier: Operating System :: OS Independent
Requires-Python: >=3.6
